search_names/__init__.py
search_names/cli.py
search_names/config.py
search_names/engines.py
search_names/enhanced_name_parser.py
search_names/logging_config.py
search_names/merge_results.py
search_names/models.py
search_names/nlp_engine.py
search_names/pipeline/__init__.py
search_names/pipeline/optimized_search.py
search_names/pipeline/step1_clean.py
search_names/pipeline/step2_augment.py
search_names/pipeline/step3_preprocess.py
search_names/pipeline/step4_search.py
search_names/split_text_corpus.py
search_names/streaming_utils.py
search_names/utils.py
search_names-0.5.0.dist-info/WHEEL
search_names-0.5.0.dist-info/entry_points.txt
search_names-0.5.0.dist-info/METADATA
search_names-0.5.0.dist-info/RECORD
