Metadata-Version: 2.3
Name: search_names
Version: 0.5.0
Summary: Advanced name search and entity recognition in large text corpora with NLP and AI capabilities
Keywords: search,names,text,corpus,pattern,ner,nlp,entity-recognition,entity-linking,fuzzy-matching
Author: Suriyan Laohaprapanon, Gaurav Sood
Author-email: Suriyan Laohaprapanon <suriyant@gmail.com>, Gaurav Sood <gsood07@gmail.com>
License: MIT
Classifier: Development Status :: 4 - Beta
Classifier: Intended Audience :: Developers
Classifier: License :: OSI Approved :: MIT License
Classifier: Programming Language :: Python :: 3.11
Classifier: Programming Language :: Python :: 3.12
Classifier: Programming Language :: Python :: 3.13
Classifier: Topic :: Scientific/Engineering :: Information Analysis
Classifier: Topic :: Software Development :: Libraries :: Python Modules
Classifier: Topic :: Utilities
Requires-Dist: nameparser>=1.1.0
Requires-Dist: python-levenshtein>=0.27.0
Requires-Dist: regex>=2024.0.0
Requires-Dist: nltk>=3.9.0
Requires-Dist: typer>=0.20.0
Requires-Dist: pydantic>=2.12.0
Requires-Dist: pyyaml>=6.0
Requires-Dist: rich>=14.0.0
Requires-Dist: parsernaam>=0.1.0
Requires-Dist: pandas>=2.3.0
Requires-Dist: spacy>=3.8.0
Requires-Dist: sentence-transformers>=5.0.0
Requires-Dist: transformers>=4.57.0 ; extra == 'all'
Requires-Dist: torch>=2.9.0 ; extra == 'all'
Requires-Dist: huggingface-hub>=0.36.0 ; extra == 'all'
Requires-Dist: scipy>=1.16.0 ; extra == 'all'
Requires-Dist: joblib>=1.5.0 ; extra == 'all'
Requires-Dist: numpy>=1.26.0 ; extra == 'all'
Requires-Dist: pyarrow>=22.0.0 ; extra == 'all'
Requires-Dist: polars>=1.35.0 ; extra == 'all'
Requires-Dist: elasticsearch>=9.0.0 ; extra == 'all'
Requires-Dist: opensearch-py>=3.0.0 ; extra == 'all'
Requires-Dist: fastapi>=0.122.0 ; extra == 'all'
Requires-Dist: uvicorn[standard]>=0.38.0 ; extra == 'all'
Requires-Dist: ruff>=0.14.0 ; extra == 'dev'
Requires-Dist: pre-commit>=4.0.0 ; extra == 'dev'
Requires-Dist: sphinx>=8.0.0 ; extra == 'docs'
Requires-Dist: furo>=2025.9.0 ; extra == 'docs'
Requires-Dist: transformers>=4.57.0 ; extra == 'enhanced'
Requires-Dist: torch>=2.9.0 ; extra == 'enhanced'
Requires-Dist: huggingface-hub>=0.36.0 ; extra == 'enhanced'
Requires-Dist: pyarrow>=22.0.0 ; extra == 'formats'
Requires-Dist: polars>=1.35.0 ; extra == 'formats'
Requires-Dist: scipy>=1.16.0 ; extra == 'nlp'
Requires-Dist: joblib>=1.5.0 ; extra == 'nlp'
Requires-Dist: numpy>=1.26.0 ; extra == 'nlp'
Requires-Dist: elasticsearch>=9.0.0 ; extra == 'search'
Requires-Dist: opensearch-py>=3.0.0 ; extra == 'search'
Requires-Dist: coverage>=7.12.0 ; extra == 'test'
Requires-Dist: pytest>=9.0.0 ; extra == 'test'
Requires-Dist: pytest-asyncio>=1.3.0 ; extra == 'test'
Requires-Dist: pytest-timeout>=2.3.1 ; extra == 'test'
Requires-Dist: fastapi>=0.122.0 ; extra == 'web'
Requires-Dist: uvicorn[standard]>=0.38.0 ; extra == 'web'
Requires-Python: >=3.11
Project-URL: Homepage, https://github.com/appeler/search-names
Project-URL: Issues, https://github.com/appeler/search-names/issues
Project-URL: Repository, https://github.com/appeler/search-names
Provides-Extra: all
Provides-Extra: dev
Provides-Extra: docs
Provides-Extra: enhanced
Provides-Extra: formats
Provides-Extra: nlp
Provides-Extra: search
Provides-Extra: test
Provides-Extra: web
